minju210_cli/__init__.py
minju210_cli/cli.py
minju210_cli-0.1.1.dist-info/METADATA
minju210_cli-0.1.1.dist-info/WHEEL
minju210_cli-0.1.1.dist-info/entry_points.txt
minju210_cli-0.1.1.dist-info/top_level.txt
minju210_cli-0.1.1.dist-info/RECORD
