Metadata-Version: 2.1
Name: minju210_cli
Version: 0.1.1
Summary: Default template for PDM package
Author-email: minju210 <juliana6190210@gmail.com>
License: MIT
Requires-Python: >=3.9
Requires-Dist: minju210-lotto >=0.2.0
